{
  "name": "Breeze Dark",
  "dark": true,
  "author": "KDE Community",
  "editorScheme": "/Breeze_Dark.xml",
  "colors": {
    "paperWhite": "#fcfcfc",
    "cardboardGray": "#eff0f1",
    "alternateGray": "#bdc3c7",

    "lazyGray": "#afb0b3",
    "coastalFog": "#a1a9b1",

    "iconGray": "#4d4d4d",
    "burntCharcoal": "#3b4045",
    "charcoalGray": "#31363b",
    "shadeBlack": "#232629",

    "hoverBlue": "#93cee9",
    "plasmaBlue": "#3daee9",
    "iconBlue": "#1d99f3",
    "abyssBlue": "#2980b9",

    "iconViolet": "#9B59B6",
    "darkerViolet": "#8E44AD",

    "dangerRed": "#ed1515",
    "iconRed": "#da4453",
    "darkerRed": "#C0392B",

    "bewareOrange": "#f67400",
    "iconOrange": "#f47750",
    "darkerOrange": "#D35400",

    "iconYellow": "#fdbc4b",
    "darkerYellow": "#F39C1F",

    "verdantGreen": "#11d116",
    "iconGreen": "#2ecc71",
    "nobleFir": "#27ae60",

    "mellowTurquoise": "#1cdc9a",
    "iconTurquoise": "#1ABC9C",
    "darkerTurquoise": "#16A085",


    "borderColorDark": "#64686b",
    "fixedHoverBlueDark": "#33779C",
    "spaceBlack": "#1B1E20",
    "alternateSpaceBlack": "#212528",
    "darkerCharcoalGray": "#2A2E32",
    "tabBackgroundDark": "#26292C"
  },

  "ui": {
    "*": {
      "background": "darkerCharcoalGray",
      "inactiveBackground": "darkerCharcoalGray",
      "disabledBackground": "darkerCharcoalGray",

      "foreground": "paperWhite",
      "disabledForeground": "coastalFog",
      "inactiveForeground": "coastalFog",
      "disabledText": "coastalFog",

      "successForeground": "nobleFir",
      "infoForeground": "alternateGray",
      "warningForeground": "bewareOrange",
      "errorForeground": "iconRed",

      "selectionBackground":  "plasmaBlue",
      "selectionInactiveBackground": "fixedHoverBlueDark",
      "selectionBackgroundInactive": "fixedHoverBlueDark",

      "selectionForeground": "paperWhite",
      "acceleratorSelectionForeground": "paperWhite",
      "selectionInactiveForeground": "cardboardGray",
      "selectionForegroundInactive": "cardboardGray",

      "modifiedItemForeground": "plasmaBlue",

      "borderColor": "borderColorDark",
      "separatorColor": "borderColorDark",
      "separatorForeground": "borderColorDark",
      "lineSeparatorColor": "borderColorDark",
      "focusedBorderColor": "plasmaBlue",
      "hoverBorderColor": "plasmaBlue",
      "pressedBorderColor": "plasmaBlue",
      "disabledBorderColor": "iconGray"
    },

    "ActionButton": {
      "hoverBackground": "fixedHoverBlueDark",
      "pressedBackground": "plasmaBlue"
    },

    "Button": {
      "startBackground": "charcoalGray",
      "endBackground": "#303439",
      "startBorderColor": "borderColorDark",
      "endBorderColor": "borderColorDark",
      "focusedBorderColor": "plasmaBlue",

      "default": {
        "foreground": "paperWhite",
        "startBackground": "plasmaBlue",
        "endBackground": "#1998da",
        "startBorderColor": "plasmaBlue",
        "endBorderColor": "#1998da",
        "focusedBorderColor": "plasmaBlue",
        "focusColor": "plasmaBlue"
      }
    },

    "Borders": {
      "color": "borderColorDark",
      "ContrastBorderColor": "borderColorDark"
    },

    "ComboBox": {
      "modifiedItemForeground": "plasmaBlue",
      "nonEditableBackground": "charcoalGray",
      "background": "spaceBlack",
      "selectionBackground": "plasmaBlue",
      "disabledForeground": "coastalFog",
      "ArrowButton": {
        "iconColor": "paperWhite",
        "disabledIconColor": "coastalFog",
        "background": "spaceBlack",
        "nonEditableBackground": "charcoalGray"
      }
    },

    "Component": {
      "errorFocusColor": "dangerRed",
      "warningFocusColor": "bewareOrange",
      "iconColor": "paperWhite"
    },

    "DefaultTabs": {
      "background": "tabBackgroundDark",
      "underlinedTabBackground": "charcoalGray",
      "underlineColor": "plasmaBlue",
      "inactiveUnderlineColor": "iconGray",
      "hoverBackground": "#2E4857"
    },

    "Editor": {
      "background": "spaceBlack",
      "shortcutForeground": "abyssBlue"
    },

    "EditorTabs": {
      "background": "tabBackgroundDark",
      "underlinedTabBackground": "charcoalGray"
    },

    "FileColor": {
      "Blue": "#223d52",
      "Violet": "#3b3045",
      "Rose": "#482c32",
      "Orange": "#4d3631",
      "Yellow": "#4f4430",
      "Green": "#254738"
    },

    "Label": {
      "infoForeground": "alternateGray",
      "errorForeground": "dangerRed"
    },

    "List.background": "spaceBlack",

    "Link": {
      "activeForeground": "abyssBlue",
      "hoverForeground": "abyssBlue",
      "pressedForeground": "abyssBlue",
      "visitedForeground": "iconViolet",
      "secondaryForeground": "iconBlue"
    },

    "MemoryIndicator": {
      "usedBackground": "plasmaBlue",
      "allocatedBackground": "lazyGray"
    },

    "Notification": {
      "background": "charcoalGray",
      "errorForeground": "dangerRed",

      "ToolWindow": {
        "informativeBackground": "#2a483b",
        "informativeBorderColor": "nobleFir",
        "informativeForeground": "paperWhite",
        "warningBackground": "#533c28",
        "warningBorderColor": "bewareOrange",
        "warningForeground": "paperWhite",
        "errorBackground": "#4e3339",
        "errorBorderColor": "iconRed",
        "errorForeground": "paperWhite"
      }
    },

    "ParameterInfo": {
      "background": "charcoalGray",
      "foreground": "cardboardGray"
    },

    "Plugins": {
      "SectionHeader.background": "charcoalGray",
      "lightSelectionBackground": "fixedHoverBlueDark",
      "tagBackground": "iconGray",
      "tagForeground": "alternateGray",
      "SearchField.background": "spaceBlack",
      "Button": {
        "installFillForeground": "paperWhite",
        "installFillBackground": "plasmaBlue",
        "installForeground": "paperWhite",
        "installBackground": "darkerCharcoalGray",
        "installBorderColor": "borderColorDark",
        "updateBackground": "plasmaBlue",
        "updateBorderColor": "plasmaBlue"
      }
    },

    "ProgressBar": {
      "progressColor": "plasmaBlue",
      "indeterminateStartColor": "plasmaBlue",
      "indeterminateEndColor": "fixedHoverBlueDark",
      "failedColor": "dangerRed",
      "passedColor": "verdantGreen"
    },

    "Popup": {
      "Header.activeBackground": "charcoalGray",
      "Header.inactiveBackground": "darkerCharcoalGray",
      "Toolbar.background": "charcoalGray",
      "Advertiser.background": "darkerCharcoalGray"
    },

    "SearchEverywhere": {
      "Header.background": "charcoalGray",
      "Tab.selectedBackground": "darkerCharcoalGray",
      "Tab.selectedForeground": "paperWhite",
      "Advertiser.background": "darkerCharcoalGray"
    },

    "SidePanel.background": "shadeBlack",

    "ScrollBar": {
      "Transparent": {
        "thumbColor": "iconGray",
        "hoverThumbColor": "plasmaBlue",
        "hoverTrackColor": "iconGray"
      },
      "thumbColor": "iconGray",
      "hoverThumbColor": "plasmaBlue",
      "trackColor": "iconGray"
    },

    "TabbedPane": {
      "background": "tabBackgroundDark",
      "focusColor": "darkerCharcoalGray",
      "hoverColor": "fixedHoverBlueDark",
      "underlineColor": "plasmaBlue",
      "disabledUnderlineColor": "iconGray"
    },

    "Table": {
      "background": "spaceBlack",
      "alternativeRowBackground": "charcoalGray",
      "gridColor": "borderColorDark"
    },

    "TitlePane.background": "charcoalGray",

    "TextArea.background": "shadeBlack",
    "TextPane.background": "shadeBlack",

    "TextField": {
      "background": "spaceBlack",
      "selectionBackground": "plasmaBlue"
    },

    "ToggleButton": {
      "background": "iconGray",
      "foreground": "paperWhite",
      "onBackground": "iconGreen",
      "onForeground": "paperWhite",
      "offBackground": "iconRed",
      "offForeground": "paperWhite"
    },

    "ToolBar.background": "charcoalGray",

    "ToolTip": {
      "background": "charcoalGray"
    },

    "ToolWindow": {
      "Header.background": "charcoalGray",
      "Button": {
        "selectedBackground": "shadeBlack",
        "hoverBackground": "fixedHoverBlueDark"
      }
    },

    "Tree.background": "shadeBlack",

    "WelcomeScreen.SidePanel.background": "shadeBlack"
  },

  "icons": {
    "ColorPalette": {
      "Actions.Grey": "#bdc3c7",
      "Actions.GreyInline": "#bdc3c7",
      "Actions.GreyInline.Dark": "#bdc3c7",
      "Actions.Blue": "#1d99f3",
      "Actions.Red": "#da4453",
      "Actions.Yellow": "#fdbc4b",
      "Actions.Green": "#2ecc71",

      "Objects.Grey": "#bdc3c7",
      "Objects.BlackText": "#232629",
      "Objects.Blue": "#1d99f3",
      "Objects.Purple": "#8e44ad",
      "Objects.RedStatus": "#ed1515",
      "Objects.Red": "#da4453",
      "Objects.Yellow": "#fdbc4b",
      "Objects.Green": "#2ecc71",

      "Checkbox.Background.Default": "#2A2E32",
      "Checkbox.Border.Default": "#afb0b3",
      "Checkbox.Background.Selected": "#2A2E32",
      "Checkbox.Foreground.Selected": "#eff0f1",
      "Checkbox.Border.Selected": "#3daee9",
      "Checkbox.Background.Disabled": "#2A2E32",
      "Checkbox.Foreground.Disabled": "#7f8c8d",
      "Checkbox.Border.Disabled": "#7f8c8d"
    }
  }
}